[
  {
    "url": "https://www.linkedin.com/company/versa-networks/",
    "status": "Success",
    "name": "Versa Networks",
    "logoUrl": "https://media.licdn.com/dms/image/v2/D4D0BAQGZGMc0hbvv1g/company-logo_200_200/company-logo_200_200/0/1711664330929/versa_networks_logo?e=2147483647&v=beta&t=IhG-_ursFDqk1I3UPtymRPkh0QPHbE4DwhVb-WyuYQg",
    "bannerUrl": null,
    "aboutUs": "Versa is the modern secure network.\n\nAvailable via the cloud, on-premises, or as a blended combination of both, Versa SASE connects Enterprise branches, teleworkers, and end users securely and reliably to applications in the cloud or data centers around the world.\n          \n\n          \n              \n    \n      \n          Website\n      \n      \n        \n                  \n    \n      http://www.versa-networks.com\n      \n  \n\n    \n  \n                  External link for Versa Networks\n                \n      \n    \n  \n              \n    \n      \n          Industry\n      \n      \n        \n                  Software Development\n                \n      \n    \n  \n              \n    \n      \n          Company size\n      \n      \n        \n                  \n\n    \n    \n    \n    \n    \n    \n    \n    \n    \n\n        501-1,000 employees\n  \n\n                \n      \n    \n  \n              \n    \n      \n          Headquarters\n      \n      \n        \n                    Santa Clara, California\n                \n      \n    \n  \n              \n    \n      \n          Type\n      \n      \n        \n                  Privately Held\n                \n      \n    \n  \n              \n    \n      \n          Founded\n      \n      \n        \n                  2012\n                \n      \n    \n  \n\n              \n    \n      \n          Specialties\n      \n      \n        \n                  SDN, SD-WAN, SD-Security, Network Security, VNF, Hybrid WAN, MSP, WAN, Multicloud, SASE, Cyber Security, CASB, SWG, NGFW, RBI, ZTNA, SSE, DLP, and AI",
    "description": "Versa is the modern secure network.\n\nAvailable via the cloud, on-premises, or as a blended combination of both, Versa SASE connects Enterprise branches, teleworkers, and end users securely and reliably to applications in the cloud or data centers around the world.\n          \n\n          \n              \n    \n      \n          Website\n      \n      \n        \n                  \n    \n      http://www.versa-networks.com\n      \n  \n\n    \n  \n                  External link for Versa Networks\n                \n      \n    \n  \n              \n    \n      \n          Industry\n      \n      \n        \n                  Software Development\n                \n      \n    \n  \n              \n    \n      \n          Company size\n      \n      \n        \n                  \n\n    \n    \n    \n    \n    \n    \n    \n    \n    \n\n        501-1,000 employees\n  \n\n                \n      \n    \n  \n              \n    \n      \n          Headquarters\n      \n      \n        \n                    Santa Clara, California\n                \n      \n    \n  \n              \n    \n      \n          Type\n      \n      \n        \n                  Privately Held\n                \n      \n    \n  \n              \n    \n      \n          Founded\n      \n      \n        \n                  2012\n                \n      \n    \n  \n\n              \n    \n      \n          Specialties\n      \n      \n        \n                  SDN, SD-WAN, SD-Security, Network Security, VNF, Hybrid WAN, MSP, WAN, Multicloud, SASE, Cyber Security, CASB, SWG, NGFW, RBI, ZTNA, SSE, DLP, and AI",
    "website": "http://www.versa-networks.com\n      \n  \n\n    \n  \n                  External link for Versa Networks",
    "verified": false,
    "verifiedPage": null,
    "industry": "Software Development",
    "type": "Software Development",
    "companySize": "501-1,000 employees",
    "employees": "501-1,000 employees",
    "headquarters": "Santa Clara, California",
    "location": "Santa Clara, California",
    "founded": "2012",
    "locations": [
      "2550 Great America Way",
      "Suite 301",
      "Santa Clara, California 95054, US"
    ],
    "specialties": [
      "SDN",
      "SD-WAN",
      "SD-Security",
      "Network Security",
      "VNF",
      "Hybrid WAN",
      "MSP",
      "WAN",
      "Multicloud",
      "SASE",
      "Cyber Security",
      "CASB",
      "SWG",
      "NGFW",
      "RBI",
      "ZTNA",
      "SSE",
      "DLP",
      "and AI"
    ]
  }
]